joytide/__init__.py
joytide/__main__.py
joytide/ascii_art.py
joytide/core.py
joytide/race.py
joytide/twenty_48.py
joytide-0.0.8.dist-info/licenses/LICENSE
joytide-0.0.8.dist-info/METADATA
joytide-0.0.8.dist-info/WHEEL
joytide-0.0.8.dist-info/entry_points.txt
joytide-0.0.8.dist-info/top_level.txt
joytide-0.0.8.dist-info/RECORD
