Metadata-Version: 2.4
Name: joytide
Version: 0.0.8
Summary: A fun Python package by team_riptide with random playful helpers.
Author-email: Saud Alsheddy <sa8429@nyu.edu>, Omer Hortig <oh2065@nyu.edu>, Amy Liu <sl9964@nyu.edu>, Alfardil Alam <aa11101@nyu.edu>, Lucy Hartigan <lmh8583@nyu.edu>
License:                     GNU GENERAL PUBLIC LICENSE
Project-URL: Homepage, https://github.com/swe-students-fall2025/3-python-package-team_riptide
Project-URL: Repository, https://github.com/swe-students-fall2025/3-python-package-team_riptide.git
Keywords: Python,fun,package
Classifier: Programming Language :: Python :: 3
Classifier: Intended Audience :: Education
Classifier: License :: OSI Approved :: GNU General Public License v3 (GPLv3)
Classifier: Operating System :: OS Independent
Requires-Python: >=3.10
License-File: LICENSE
Requires-Dist: colorama>=0.4.6
Requires-Dist: readchar>=4.0.0
Provides-Extra: dev
Requires-Dist: pytest; extra == "dev"
Dynamic: license-file
